conda_quetz_auth/__init__.py
conda_quetz_auth/constants.py
conda_quetz_auth/plugin.py
conda_quetz_auth-1.0.3.dist-info/METADATA
conda_quetz_auth-1.0.3.dist-info/WHEEL
conda_quetz_auth-1.0.3.dist-info/entry_points.txt
conda_quetz_auth-1.0.3.dist-info/top_level.txt
conda_quetz_auth-1.0.3.dist-info/RECORD
