Metadata-Version: 2.1
Name: conda-quetz-auth
Version: 1.0.3
Summary: Conda plugin for quetz to authenticate users
Requires-Python: >=3.9
